{
  "encoder/task_auroc": 0.905451388888889,
  "encoder/recon_cosine": 0.9984248876571655,
  "encoder/alpha_r2": -6.354180240631104,
  "n_folds": 5,
  "n_samples": 300,
  "M": 144,
  "S": 11,
  "args": {
    "model_name": "gpt2",
    "data_dir": null,
    "num_prompts": 60,
    "cache_dir": "outputs/features",
    "no_cache": false,
    "patch_depth": 1,
    "heads_per_patch": 1,
    "alpha": 1,
    "encoder_type": "transformer",
    "embed_dim": 256,
    "hidden_dim": 256,
    "n_hidden_layers": 2,
    "n_attn_heads": 4,
    "dropout": 0,
    "lr": 0.00015004658504812004,
    "weight_decay": 0.000740958402225501,
    "batch_size": 32,
    "max_epochs": 100,
    "n_cv_folds": 5,
    "objective_task_weight": 2,
    "objective_recon_weight": 0.5,
    "objective_alpha_weight": 0,
    "wandb_project": null
  }
}